<?xml version="1.0" encoding="UTF-8"?>
<!DOCTYPE mapper PUBLIC "-//mybatis.org//DTD Mapper 3.0//EN" "http://mybatis.org/dtd/mybatis-3-mapper.dtd">
<mapper namespace="com.styz.api.mapper.PermissionResourceMapper">
  <resultMap id="BaseResultMap" type="com.styz.api.model.PermissionResource">
    <!--
      WARNING - @mbg.generated
      This element is automatically generated by MyBatis Generator, do not modify.
    -->
    <id column="gid" jdbcType="BIGINT" property="gid" />
    <result column="parentResourceId" jdbcType="BIGINT" property="parentresourceid" />
    <result column="parentResourceIds" jdbcType="VARCHAR" property="parentresourceids" />
    <result column="resourceId" jdbcType="VARCHAR" property="resourceid" />
    <result column="resourceHref" jdbcType="VARCHAR" property="resourcehref" />
    <result column="resourceCssClass" jdbcType="VARCHAR" property="resourcecssclass" />
    <result column="resourceIcon" jdbcType="VARCHAR" property="resourceicon" />
    <result column="resourceType" jdbcType="INTEGER" property="resourcetype" />
    <result column="resourceStatus" jdbcType="INTEGER" property="resourcestatus" />
    <result column="menuType" jdbcType="INTEGER" property="menutype" />
    <result column="menuSort" jdbcType="INTEGER" property="menusort" />
    <result column="resourceName" jdbcType="VARCHAR" property="resourcename" />
    <result column="createTime" jdbcType="BIGINT" property="createtime" />
    <result column="updateTime" jdbcType="BIGINT" property="updatetime" />
  </resultMap>
  <resultMap extends="BaseResultMap" id="ResultMapWithBLOBs" type="com.styz.api.model.PermissionResource">
    <!--
      WARNING - @mbg.generated
      This element is automatically generated by MyBatis Generator, do not modify.
    -->
    <result column="resourceDesc" jdbcType="LONGVARCHAR" property="resourcedesc" />
  </resultMap>
  <sql id="Base_Column_List">
    <!--
      WARNING - @mbg.generated
      This element is automatically generated by MyBatis Generator, do not modify.
    -->
    gid, parentResourceId, parentResourceIds, resourceId, resourceHref, resourceCssClass, 
    resourceIcon, resourceType, resourceStatus, menuType, menuSort, resourceName, createTime, 
    updateTime
  </sql>
  <sql id="Blob_Column_List">
    <!--
      WARNING - @mbg.generated
      This element is automatically generated by MyBatis Generator, do not modify.
    -->
    resourceDesc
  </sql>
  <select id="selectByPrimaryKey" parameterType="java.lang.Long" resultMap="ResultMapWithBLOBs">
    <!--
      WARNING - @mbg.generated
      This element is automatically generated by MyBatis Generator, do not modify.
    -->
    select 
    <include refid="Base_Column_List" />
    ,
    <include refid="Blob_Column_List" />
    from permission_resource
    where gid = #{gid,jdbcType=BIGINT}
  </select>
  <delete id="deleteByPrimaryKey" parameterType="java.lang.Long">
    <!--
      WARNING - @mbg.generated
      This element is automatically generated by MyBatis Generator, do not modify.
    -->
    delete from permission_resource
    where gid = #{gid,jdbcType=BIGINT}
  </delete>
  <insert id="insert" parameterType="com.styz.api.model.PermissionResource">
    <!--
      WARNING - @mbg.generated
      This element is automatically generated by MyBatis Generator, do not modify.
    -->
    insert into permission_resource (gid, parentResourceId, parentResourceIds, 
      resourceId, resourceHref, resourceCssClass, 
      resourceIcon, resourceType, resourceStatus, 
      menuType, menuSort, resourceName, 
      createTime, updateTime, resourceDesc
      )
    values (#{gid,jdbcType=BIGINT}, #{parentresourceid,jdbcType=BIGINT}, #{parentresourceids,jdbcType=VARCHAR}, 
      #{resourceid,jdbcType=VARCHAR}, #{resourcehref,jdbcType=VARCHAR}, #{resourcecssclass,jdbcType=VARCHAR}, 
      #{resourceicon,jdbcType=VARCHAR}, #{resourcetype,jdbcType=INTEGER}, #{resourcestatus,jdbcType=INTEGER}, 
      #{menutype,jdbcType=INTEGER}, #{menusort,jdbcType=INTEGER}, #{resourcename,jdbcType=VARCHAR}, 
      #{createtime,jdbcType=BIGINT}, #{updatetime,jdbcType=BIGINT}, #{resourcedesc,jdbcType=LONGVARCHAR}
      )
  </insert>
  <insert id="insertSelective" parameterType="com.styz.api.model.PermissionResource">
    <!--
      WARNING - @mbg.generated
      This element is automatically generated by MyBatis Generator, do not modify.
    -->
    insert into permission_resource
    <trim prefix="(" suffix=")" suffixOverrides=",">
      <if test="gid != null">
        gid,
      </if>
      <if test="parentresourceid != null">
        parentResourceId,
      </if>
      <if test="parentresourceids != null">
        parentResourceIds,
      </if>
      <if test="resourceid != null">
        resourceId,
      </if>
      <if test="resourcehref != null">
        resourceHref,
      </if>
      <if test="resourcecssclass != null">
        resourceCssClass,
      </if>
      <if test="resourceicon != null">
        resourceIcon,
      </if>
      <if test="resourcetype != null">
        resourceType,
      </if>
      <if test="resourcestatus != null">
        resourceStatus,
      </if>
      <if test="menutype != null">
        menuType,
      </if>
      <if test="menusort != null">
        menuSort,
      </if>
      <if test="resourcename != null">
        resourceName,
      </if>
      <if test="createtime != null">
        createTime,
      </if>
      <if test="updatetime != null">
        updateTime,
      </if>
      <if test="resourcedesc != null">
        resourceDesc,
      </if>
    </trim>
    <trim prefix="values (" suffix=")" suffixOverrides=",">
      <if test="gid != null">
        #{gid,jdbcType=BIGINT},
      </if>
      <if test="parentresourceid != null">
        #{parentresourceid,jdbcType=BIGINT},
      </if>
      <if test="parentresourceids != null">
        #{parentresourceids,jdbcType=VARCHAR},
      </if>
      <if test="resourceid != null">
        #{resourceid,jdbcType=VARCHAR},
      </if>
      <if test="resourcehref != null">
        #{resourcehref,jdbcType=VARCHAR},
      </if>
      <if test="resourcecssclass != null">
        #{resourcecssclass,jdbcType=VARCHAR},
      </if>
      <if test="resourceicon != null">
        #{resourceicon,jdbcType=VARCHAR},
      </if>
      <if test="resourcetype != null">
        #{resourcetype,jdbcType=INTEGER},
      </if>
      <if test="resourcestatus != null">
        #{resourcestatus,jdbcType=INTEGER},
      </if>
      <if test="menutype != null">
        #{menutype,jdbcType=INTEGER},
      </if>
      <if test="menusort != null">
        #{menusort,jdbcType=INTEGER},
      </if>
      <if test="resourcename != null">
        #{resourcename,jdbcType=VARCHAR},
      </if>
      <if test="createtime != null">
        #{createtime,jdbcType=BIGINT},
      </if>
      <if test="updatetime != null">
        #{updatetime,jdbcType=BIGINT},
      </if>
      <if test="resourcedesc != null">
        #{resourcedesc,jdbcType=LONGVARCHAR},
      </if>
    </trim>
  </insert>
  <update id="updateByPrimaryKeySelective" parameterType="com.styz.api.model.PermissionResource">
    <!--
      WARNING - @mbg.generated
      This element is automatically generated by MyBatis Generator, do not modify.
    -->
    update permission_resource
    <set>
      <if test="parentresourceid != null">
        parentResourceId = #{parentresourceid,jdbcType=BIGINT},
      </if>
      <if test="parentresourceids != null">
        parentResourceIds = #{parentresourceids,jdbcType=VARCHAR},
      </if>
      <if test="resourceid != null">
        resourceId = #{resourceid,jdbcType=VARCHAR},
      </if>
      <if test="resourcehref != null">
        resourceHref = #{resourcehref,jdbcType=VARCHAR},
      </if>
      <if test="resourcecssclass != null">
        resourceCssClass = #{resourcecssclass,jdbcType=VARCHAR},
      </if>
      <if test="resourceicon != null">
        resourceIcon = #{resourceicon,jdbcType=VARCHAR},
      </if>
      <if test="resourcetype != null">
        resourceType = #{resourcetype,jdbcType=INTEGER},
      </if>
      <if test="resourcestatus != null">
        resourceStatus = #{resourcestatus,jdbcType=INTEGER},
      </if>
      <if test="menutype != null">
        menuType = #{menutype,jdbcType=INTEGER},
      </if>
      <if test="menusort != null">
        menuSort = #{menusort,jdbcType=INTEGER},
      </if>
      <if test="resourcename != null">
        resourceName = #{resourcename,jdbcType=VARCHAR},
      </if>
      <if test="createtime != null">
        createTime = #{createtime,jdbcType=BIGINT},
      </if>
      <if test="updatetime != null">
        updateTime = #{updatetime,jdbcType=BIGINT},
      </if>
      <if test="resourcedesc != null">
        resourceDesc = #{resourcedesc,jdbcType=LONGVARCHAR},
      </if>
    </set>
    where gid = #{gid,jdbcType=BIGINT}
  </update>
  <update id="updateByPrimaryKeyWithBLOBs" parameterType="com.styz.api.model.PermissionResource">
    <!--
      WARNING - @mbg.generated
      This element is automatically generated by MyBatis Generator, do not modify.
    -->
    update permission_resource
    set parentResourceId = #{parentresourceid,jdbcType=BIGINT},
      parentResourceIds = #{parentresourceids,jdbcType=VARCHAR},
      resourceId = #{resourceid,jdbcType=VARCHAR},
      resourceHref = #{resourcehref,jdbcType=VARCHAR},
      resourceCssClass = #{resourcecssclass,jdbcType=VARCHAR},
      resourceIcon = #{resourceicon,jdbcType=VARCHAR},
      resourceType = #{resourcetype,jdbcType=INTEGER},
      resourceStatus = #{resourcestatus,jdbcType=INTEGER},
      menuType = #{menutype,jdbcType=INTEGER},
      menuSort = #{menusort,jdbcType=INTEGER},
      resourceName = #{resourcename,jdbcType=VARCHAR},
      createTime = #{createtime,jdbcType=BIGINT},
      updateTime = #{updatetime,jdbcType=BIGINT},
      resourceDesc = #{resourcedesc,jdbcType=LONGVARCHAR}
    where gid = #{gid,jdbcType=BIGINT}
  </update>
  <update id="updateByPrimaryKey" parameterType="com.styz.api.model.PermissionResource">
    <!--
      WARNING - @mbg.generated
      This element is automatically generated by MyBatis Generator, do not modify.
    -->
    update permission_resource
    set parentResourceId = #{parentresourceid,jdbcType=BIGINT},
      parentResourceIds = #{parentresourceids,jdbcType=VARCHAR},
      resourceId = #{resourceid,jdbcType=VARCHAR},
      resourceHref = #{resourcehref,jdbcType=VARCHAR},
      resourceCssClass = #{resourcecssclass,jdbcType=VARCHAR},
      resourceIcon = #{resourceicon,jdbcType=VARCHAR},
      resourceType = #{resourcetype,jdbcType=INTEGER},
      resourceStatus = #{resourcestatus,jdbcType=INTEGER},
      menuType = #{menutype,jdbcType=INTEGER},
      menuSort = #{menusort,jdbcType=INTEGER},
      resourceName = #{resourcename,jdbcType=VARCHAR},
      createTime = #{createtime,jdbcType=BIGINT},
      updateTime = #{updatetime,jdbcType=BIGINT}
    where gid = #{gid,jdbcType=BIGINT}
  </update>
    <select id="findPermissionResourceByResoureIds" resultMap="BaseResultMap">
      select * from permission_resource
      where gid in
      <foreach close=")" collection="resourceIds" index="index" item="item" open="(" separator=",">
        #{item}
      </foreach>
      and resourceStatus=1
    </select>
  <select id="findPermissionResourceByResourcetypeAndInResourceid" resultMap="BaseResultMap">
    select * from permission_resource
    where gid in
    <foreach close=")" collection="resourceIds" index="index" item="item" open="(" separator=",">
      #{item}
    </foreach>
    and resourceType=#{resourceType,jdbcType=INTEGER}
    and resourceStatus=1
    order by menuSort asc
  </select>
</mapper>